bitvavo_api_upgraded/__init__.py
bitvavo_api_upgraded/bitvavo.py
bitvavo_api_upgraded/dataframe_utils.py
bitvavo_api_upgraded/helper_funcs.py
bitvavo_api_upgraded/py.typed
bitvavo_api_upgraded/settings.py
bitvavo_api_upgraded/type_aliases.py
bitvavo_client/__init__.py
bitvavo_client/adapters/__init__.py
bitvavo_client/adapters/returns_adapter.py
bitvavo_client/auth/__init__.py
bitvavo_client/auth/rate_limit.py
bitvavo_client/auth/signing.py
bitvavo_client/core/__init__.py
bitvavo_client/core/errors.py
bitvavo_client/core/model_preferences.py
bitvavo_client/core/private_models.py
bitvavo_client/core/public_models.py
bitvavo_client/core/settings.py
bitvavo_client/core/types.py
bitvavo_client/core/validation_helpers.py
bitvavo_client/df/__init__.py
bitvavo_client/df/convert.py
bitvavo_client/endpoints/__init__.py
bitvavo_client/endpoints/base.py
bitvavo_client/endpoints/common.py
bitvavo_client/endpoints/private.py
bitvavo_client/endpoints/public.py
bitvavo_client/facade.py
bitvavo_client/py.typed
bitvavo_client/schemas/__init__.py
bitvavo_client/schemas/private_schemas.py
bitvavo_client/schemas/public_schemas.py
bitvavo_client/transport/__init__.py
bitvavo_client/transport/http.py
bitvavo_client/ws/__init__.py
bitvavo_api_upgraded-4.4.1.dist-info/WHEEL
bitvavo_api_upgraded-4.4.1.dist-info/METADATA
bitvavo_api_upgraded-4.4.1.dist-info/RECORD
