Metadata-Version: 2.3
Name: bitvavo-api-upgraded
Version: 4.4.1
Summary: A unit-tested fork of the Bitvavo API
Author: Bitvavo BV (original code), NostraDavid
Author-email: NostraDavid <55331731+NostraDavid@users.noreply.github.com>
License: ISC License
Classifier: Development Status :: 5 - Production/Stable
Classifier: Environment :: Console
Classifier: Framework :: Pytest
Classifier: Intended Audience :: Developers
Classifier: Intended Audience :: Financial and Insurance Industry
Classifier: License :: OSI Approved :: ISC License (ISCL)
Classifier: Operating System :: MacOS :: MacOS X
Classifier: Operating System :: Microsoft :: Windows
Classifier: Operating System :: POSIX
Classifier: Programming Language :: Python :: 3.9
Classifier: Programming Language :: Python :: 3.10
Classifier: Programming Language :: Python :: 3.11
Classifier: Programming Language :: Python :: 3.12
Classifier: Programming Language :: Python :: 3.13
Classifier: Programming Language :: Python
Classifier: Typing :: Typed
Requires-Dist: httpx>=0.28.1
Requires-Dist: pydantic-settings>=2.6
Requires-Dist: requests>=2.26
Requires-Dist: returns>=0.23.0
Requires-Dist: structlog>=21.5
Requires-Dist: websocket-client>=1.2
Requires-Dist: cudf-cu12>=24.0.0 ; extra == 'cudf'
Requires-Dist: narwhals>=2.0.0 ; extra == 'cudf'
Requires-Dist: narwhals[dask]>=2.0.0 ; extra == 'dask'
Requires-Dist: narwhals[duckdb]>=2.0.0 ; extra == 'duckdb'
Requires-Dist: narwhals[ibis]>=2.0.0 ; extra == 'ibis'
Requires-Dist: narwhals[modin]>=2.0.0 ; extra == 'modin'
Requires-Dist: narwhals[pandas]>=2.0.0 ; extra == 'pandas'
Requires-Dist: narwhals[polars]>=2.0.0 ; extra == 'polars'
Requires-Dist: cudf-polars-cu12>=24.0.0 ; extra == 'polars-gpu'
Requires-Dist: polars ; extra == 'polars-gpu'
Requires-Dist: narwhals>=2.0.0 ; extra == 'polars-gpu'
Requires-Dist: narwhals[pyarrow]>=2.0.0 ; extra == 'pyarrow'
Requires-Dist: narwhals[pyspark]>=2.0.0 ; extra == 'pyspark'
Requires-Dist: narwhals[pyspark-connect]>=2.0.0 ; extra == 'pyspark-connect'
Requires-Dist: narwhals[sqlframe]>=2.0.0 ; extra == 'sqlframe'
Maintainer: NostraDavid
Maintainer-email: NostraDavid <55331731+NostraDavid@users.noreply.github.com>
Requires-Python: >=3.10
Project-URL: changelog, https://github.com/Thaumatorium/bitvavo-api-upgraded/blob/master/CHANGELOG.md
Project-URL: homepage, https://github.com/Thaumatorium/bitvavo-api-upgraded
Project-URL: repository, https://github.com/Thaumatorium/bitvavo-api-upgraded
Provides-Extra: cudf
Provides-Extra: dask
Provides-Extra: duckdb
Provides-Extra: ibis
Provides-Extra: modin
Provides-Extra: pandas
Provides-Extra: polars
Provides-Extra: polars-gpu
Provides-Extra: pyarrow
Provides-Extra: pyspark
Provides-Extra: pyspark-connect
Provides-Extra: sqlframe
